setup.py
gapi_python.egg-info/PKG-INFO
gapi_python.egg-info/SOURCES.txt
gapi_python.egg-info/dependency_links.txt
gapi_python.egg-info/requires.txt
gapi_python.egg-info/top_level.txt
gapipy/__init__.py