Metadata-Version: 1.0
Name: gapi-python
Version: 0.0.5
Summary: Python client for the G Adventures REST API
Home-page: UNKNOWN
Author: G Adventures
Author-email: software@gadventures.com
License: UNKNOWN
Platform: UNKNOWN
